akkdict/__init__.py
akkdict/akkdict.py
akkdict/conf.ini
akkdict/fetchcad.py
akkdict/pagefinder.py
akkdict/indicies/ahw.csv
akkdict/indicies/cad.csv
akkdict/indicies/cda.csv
akkdict-0.1.0.dist-info/DESCRIPTION.rst
akkdict-0.1.0.dist-info/METADATA
akkdict-0.1.0.dist-info/RECORD
akkdict-0.1.0.dist-info/WHEEL
akkdict-0.1.0.dist-info/entry_points.txt
akkdict-0.1.0.dist-info/metadata.json
akkdict-0.1.0.dist-info/top_level.txt
