Metadata-Version: 2.0
Name: akkdict
Version: 0.1.0
Summary: simple utility for looking up Akkadian words in the CAD
Home-page: https://github.com/ninjaaron/akkdict
Author: Aaron Christianson
Author-email: ninjaaron@gmail.com
License: BSD
Keywords: Akkadian Chicago Assyrian Dictionary
Platform: UNKNOWN
Requires-Dist: Click
